mo_mkdocs_helm_plugin/__init__.py
mo_mkdocs_helm_plugin/__main__.py
mo_mkdocs_helm_plugin/repository.py
mo_mkdocs_helm_plugin-0.1.1.dist-info/entry_points.txt
mo_mkdocs_helm_plugin-0.1.1.dist-info/LICENSE
mo_mkdocs_helm_plugin-0.1.1.dist-info/WHEEL
mo_mkdocs_helm_plugin-0.1.1.dist-info/METADATA
mo_mkdocs_helm_plugin-0.1.1.dist-info/RECORD
