Metadata-Version: 2.1
Name: mo-mkdocs-helm-plugin
Version: 0.1.1
Summary: A mkdocs plugin to enable serving a helm chart via a github page
Home-page: https://github.com/moabu/mo-mkdocs-helm-plugin
License: Apache Software License 2.0
Author: moabu
Author-email: 47318409+moabu@users.noreply.github.com
Requires-Python: >=3.7,<4.0
Classifier: Development Status :: 3 - Alpha
Classifier: Intended Audience :: Developers
Classifier: License :: OSI Approved :: Apache Software License
Classifier: License :: Other/Proprietary License
Classifier: Operating System :: OS Independent
Classifier: Programming Language :: Python :: 3
Classifier: Programming Language :: Python :: 3.10
Classifier: Programming Language :: Python :: 3.7
Classifier: Programming Language :: Python :: 3.8
Classifier: Programming Language :: Python :: 3.9
Classifier: Topic :: Software Development :: Libraries :: Python Modules
Requires-Dist: importlib_metadata (>=4.5.0,<5.0.0); python_version < "3.8"
Requires-Dist: mkdocs (>=1.3.1,<2.0.0)
Requires-Dist: rich (>=10.14.0,<11.0.0)
Requires-Dist: typer[all] (>=0.4.0,<0.5.0)
Project-URL: Repository, https://github.com/moabu/mo-mkdocs-helm-plugin
